{
  "$schema": "https://ui.shadcn.com/schema/registry-item.json",
  "name": "file-actions",
  "type": "registry:block",
  "title": "File Actions",
  "description": "Dropdown menu with rename / move / copy / delete actions. Optimistic updates with rollback. Built on useFileActions from @file-next/headless.",
  "categories": ["files", "menus"],
  "registryDependencies": ["@file-next/headless"],
  "dependencies": [
    "lucide-react",
    "@radix-ui/react-dropdown-menu",
    "@radix-ui/react-alert-dialog"
  ],
  "files": [
    {
      "path": "registry/components/file-next/file-actions.tsx",
      "type": "registry:component",
      "target": "@components/file-next/file-actions.tsx"
    }
  ]
}
